drill.py
drill-1.2.0.dist-info/LICENSE
drill-1.2.0.dist-info/METADATA
drill-1.2.0.dist-info/WHEEL
drill-1.2.0.dist-info/top_level.txt
drill-1.2.0.dist-info/RECORD
