Metadata-Version: 2.1
Name: drill
Version: 1.2.0
Summary: A small python library for quickly traversing XML data.
Home-page: https://github.com/dcwatson/drill
Author: Dan Watson
Author-email: dcwatson@gmail.com
License: BSD
Platform: UNKNOWN
Classifier: Development Status :: 5 - Production/Stable
Classifier: Intended Audience :: Developers
Classifier: License :: OSI Approved :: BSD License
Classifier: Programming Language :: Python
Classifier: Programming Language :: Python :: 3
Classifier: Topic :: Text Processing :: Markup
